  3           0 RESUME                   0

  4           2 LOAD_CONST               1 ('010000110100001110000110000110101101010101010001001000110010001101000110000110011100100110010010010101010101010110101010101010000100010001000010010011110100111110011110011110111101101110110100100101101001011000101101101101111011100110011001001100010011000101100011100011000110011001101110110010011100100110010011010011010110100110010011011000000110000011000001000001110011100110010010010111110101111110111110111110111101100010001001001101100011011001101100101100001000011001100000000110000001100000110000110000100001011101110100100011101000111000011101011101111011100110011010010001110100011110001110001110011100100010001100100110101001101000110101110101111011111011101101101100001011000001100001100001100011000100010110110101101101011010101100101100111001100110011010010111110101111110111110111110111101110111010100100110101001101000110101110101011010110011001010010011000100110010011000011000100001011001100101101011101010111001011100011100111001101110111001001101010011010101101011101011110111110111011011011110110111101111110111110111001110000000000110110011011100110110011011011011100111001000100011011010000110100011010001010001110011101010100011011010010110100111010010010010110101101110111000000111000001110000111001111001010010101110111110110111001101110010111001111001100011011101111001001001100010011001001101001101011010101110111010010000110100001110000110000110011100110111011011011010100110101011010101010101111011111011100110110000011100000110000011000011010110111011100110110110001101100010110001110001110011110011001010010111110101111110111110111110111101110111010100100110101001101000110101110101011010110011001010010110010101100110110010110010000100010101011111111011001110110011011000011000100001001100111100100101011001010100101011101011110111110111011011011100010111000111100011100011000110000000001110110010011100100110010011010011010110110111010110110100101101001010100101100101101011001000101001001101010011010101101010101010100101011101111100100110011001100100110010110010000100011001100000000011100000111000011100011100001000001100110000000011000000110000011001011001000010000100011100100101101001011000101100101100101001010001001110110010111100101110010110010110011100110011000110110111001101110010111001111001100011001100110011011100100111001011100101100101111011111011101')
              4 STORE_FAST               0 (output)

  6           6 LOAD_CONST               2 ('')
              8 BUILD_LIST               1
             10 LOAD_GLOBAL              1 (NULL + len)
             20 LOAD_FAST                0 (output)
             22 CALL                     1
             30 BINARY_OP                5 (*)
             34 STORE_FAST               1 (encrypted)

  7          36 LOAD_CONST               3 (0)
             38 STORE_FAST               2 (i)

  8          40 LOAD_CONST               3 (0)
             42 STORE_FAST               3 (step)

  9          44 LOAD_CONST               3 (0)
             46 STORE_FAST               4 (index)

 11          48 LOAD_FAST                2 (i)
             50 LOAD_GLOBAL              1 (NULL + len)
             60 LOAD_FAST                0 (output)
             62 CALL                     1
             70 COMPARE_OP               2 (<)
             74 POP_JUMP_IF_FALSE       47 (to 170)

 12     >>   76 LOAD_FAST                0 (output)
             78 LOAD_FAST                4 (index)
             80 LOAD_FAST                4 (index)
             82 LOAD_CONST               4 (8)
             84 BINARY_OP                0 (+)
             88 BINARY_SLICE
             90 LOAD_FAST                1 (encrypted)
             92 LOAD_FAST                2 (i)
             94 LOAD_FAST                2 (i)
             96 LOAD_CONST               4 (8)
             98 BINARY_OP                0 (+)
            102 STORE_SLICE

 13         104 LOAD_FAST                4 (index)
            106 LOAD_CONST               4 (8)
            108 BINARY_OP               13 (+=)
            112 STORE_FAST               4 (index)

 14         114 LOAD_FAST                2 (i)
            116 LOAD_FAST                3 (step)
            118 BINARY_OP               13 (+=)
            122 STORE_FAST               2 (i)

 15         124 LOAD_FAST                3 (step)
            126 LOAD_CONST               5 (1)
            128 BINARY_OP                0 (+)
            132 LOAD_CONST               6 (6)
            134 BINARY_OP                6 (%)
            138 STORE_FAST               3 (step)

 11         140 LOAD_FAST                2 (i)
            142 LOAD_GLOBAL              1 (NULL + len)
            152 LOAD_FAST                0 (output)
            154 CALL                     1
            162 COMPARE_OP               2 (<)
            166 POP_JUMP_IF_FALSE        1 (to 170)
            168 JUMP_BACKWARD           47 (to 76)

 17     >>  170 LOAD_CONST               2 ('')
            172 LOAD_ATTR                3 (NULL|self + join)
            192 LOAD_FAST                1 (encrypted)
            194 CALL                     1
            202 STORE_FAST               1 (encrypted)

 18         204 LOAD_GLOBAL              5 (NULL + range)
            214 LOAD_CONST               3 (0)
            216 LOAD_GLOBAL              1 (NULL + len)
            226 LOAD_FAST                1 (encrypted)
            228 CALL                     1
            236 LOAD_CONST               4 (8)
            238 CALL                     3
            246 GET_ITER
            248 LOAD_FAST_AND_CLEAR      2 (i)
            250 SWAP                     2
            252 BUILD_LIST               0
            254 SWAP                     2
        >>  256 FOR_ITER                44 (to 348)
            260 STORE_FAST               2 (i)
            262 LOAD_GLOBAL              7 (NULL + chr)
            272 LOAD_GLOBAL              9 (NULL + int)
            282 LOAD_CONST               2 ('')
            284 LOAD_ATTR                3 (NULL|self + join)
            304 LOAD_FAST                1 (encrypted)
            306 LOAD_FAST                2 (i)
            308 LOAD_FAST                2 (i)
            310 LOAD_CONST               4 (8)
            312 BINARY_OP                0 (+)
            316 BINARY_SLICE
            318 CALL                     1
            326 LOAD_CONST               7 (2)
            328 CALL                     2
            336 CALL                     1
            344 LIST_APPEND              2
            346 JUMP_BACKWARD           46 (to 256)
        >>  348 END_FOR
            350 STORE_FAST               1 (encrypted)
            352 STORE_FAST               2 (i)

 19         354 LOAD_CONST               2 ('')
            356 LOAD_ATTR                3 (NULL|self + join)
            376 LOAD_FAST                1 (encrypted)
            378 CALL                     1
            386 STORE_FAST               1 (encrypted)

 20         388 LOAD_GLOBAL             11 (NULL + print)
            398 LOAD_FAST                1 (encrypted)
            400 CALL                     1
            408 POP_TOP
            410 RETURN_CONST             0 (None)
        >>  412 SWAP                     2
            414 POP_TOP

 18         416 SWAP                     2
            418 STORE_FAST               2 (i)
            420 RERAISE                  0
ExceptionTable:
  252 to 348 -> 412 [2]
None
